hqporner_api/__init__.py
hqporner_api/api.py
hqporner_api/modules/__init__.py
hqporner_api/modules/consts.py
hqporner_api/modules/errors.py
hqporner_api/modules/locals.py
hqporner_api/tests/__init__.py
hqporner_api/tests/test_client.py
hqporner_api/tests/test_download.py
hqporner_api/tests/test_search.py
hqporner_api/tests/test_video.py
hqporner_api-1.8.dist-info/licenses/LICENSE
hqporner_api-1.8.dist-info/METADATA
hqporner_api-1.8.dist-info/WHEEL
hqporner_api-1.8.dist-info/entry_points.txt
hqporner_api-1.8.dist-info/top_level.txt
hqporner_api-1.8.dist-info/RECORD
