Metadata-Version: 2.4
Name: hqporner_api
Version: 1.8
Summary: A Python API for the Porn Site HQPorner.com
Author-email: Johannes Habel <EchterAlsFake@proton.me>
License: LGPLv3
Project-URL: Homepage, https://github.com/EchterAlsFake/hqporner_api
Classifier: License :: OSI Approved :: GNU Lesser General Public License v3 (LGPLv3)
Classifier: Programming Language :: Python
Requires-Python: >=3.6
License-File: LICENSE
Requires-Dist: bs4
Requires-Dist: eaf_base_api
Requires-Dist: lxml
Requires-Dist: h2
Requires-Dist: brotli
Dynamic: license-file
